{
  "version": "2026.07.22",
  "updated_at": "2026-07-22T15:07:03+08:00",
  "items": [
    {
      "type": "feature",
      "text": "优化普通画布与智能画布的拖拽、缩放、连线和选择等高频交互，提升复杂画布的操作流畅性"
    },
    {
      "type": "feature",
      "text": "优化图片聊天的输入、图片预览与消息渲染性能，减少长对话中的界面卡顿"
    },
    {
      "type": "feature",
      "text": "桌面客户端限制为单实例运行，重复启动时自动聚焦已有窗口"
    },
    {
      "type": "feature",
      "text": "修复提示词素材标签删除与素材预览遮挡输入框的问题"
    },
    {
      "type": "feature",
      "text": "优化视频素材上传与地址兼容，优先返回实际可访问链接并正确处理内网地址"
    }
  ]
}
